{
  "date": "2025-10-12",
  "title": "Les voyages – Jeanne Moreau",
  "comment": "<p>柔らかな響きの木管とヴィブラフォンが軽やかに駆ける。<br>映画的な陰影と温かな歌声が印象的な一曲。</p><p>Soft-toned woodwinds and vibraphone glide lightly.<br>Cinematic shading and a warm vocal make this track memorable.</p>",
  "apple_music_embed": "https://embed.music.apple.com/jp/album/les-voyages/1443876079?i=1443876088",
  "season": [
    "fall",
    "winter"
  ],
  "weather": [
    "cloudy",
    "rainy"
  ],
  "mood": [
    "low",
    "mid"
  ],
  "country": [
    "France"
  ],
  "city": [
    "Paris"
  ]
}