{
  "date": "2026-07-14",
  "title": "Night Train To Dixie – Hugo Montenegro",
  "comment": "<p>不穏な電子音の気配と、サントラらしい緊張感のあるムード。<br>アメリカーナの影をまとった、奇妙な余韻が残る一曲。</p><p>A tense atmosphere of unsettling electronics,<br>A track that lingers with an Americana shadow.</p>",
  "apple_music_embed": "https://embed.music.apple.com/jp/album/the-night-they-drove-old-dixie-down/1568631651?i=1568631939",
  "season": [
    "fall",
    "winter"
  ],
  "weather": [
    "cloudy"
  ],
  "mood": [
    "low",
    "mid"
  ],
  "country": [
    "USA"
  ],
  "city": [
    "New York"
  ]
}
