{
  "date": "2026-01-22",
  "title": "The Sophisticated Hippie (Easy Mo Bee Remix) – Horace Silver",
  "comment": "<p>ジャズファンク寄りのリフと太いビートがじわじわと反復する。<br>70sブルーノートのムードと90sヒップホップの質感が溶け合う一曲。</p><p>Jazz-funk riffs ride over a thick, repeating beat.<br>70s Blue Note vibes merge with the gritty feel of 90s hip-hop on this hybrid cut, too.</p>",
  "apple_music_embed": "https://embed.music.apple.com/jp/album/the-sophisticated-hippie-easy-mo-bee-remix/1444200869?i=1444201117",
  "season": [
    "fall",
    "winter"
  ],
  "weather": [
    "cloudy",
    "rainy"
  ],
  "mood": [
    "mid",
    "high"
  ],
  "country": [
    "USA"
  ],
  "city": [
    "New York"
  ]
}
