{
  "date": "2026-07-15",
  "title": "Soul Makossa – Babatunde Olatunji",
  "comment": "<p>力強いパーカッションの粒立ちと、アフロ・ファンク寄りの熱いグルーヴ。<br>声とリズムが重なりながら、じわじわ高揚していく一曲。</p><p>Powerful percussion and an Afro-funk groove.<br>A track that builds excitement, filling the room.</p>",
  "apple_music_embed": "https://embed.music.apple.com/jp/album/soul-makossa/279570209?i=279570305",
  "season": [
    "summer"
  ],
  "weather": [
    "sunny",
    "cloudy"
  ],
  "mood": [
    "mid",
    "high"
  ],
  "country": [
    "Nigeria"
  ],
  "city": [
    "Ajido"
  ]
}
