{
  "date": "2026-02-05",
  "title": "Hang On In There – Mike James Kirkland",
  "comment": "<p>柔らかなリードとコーラスがミッドグルーヴの上で波打つ。<br>ドラムとベースにオーケストレーションが徐々に乗り、じっくりとピークへ向かう一曲。</p><p>Soft lead vocals and chorus swell and wave over a mid-tempo groove.<br>Orchestration gradually joins the drums and bass, building patiently toward a peak.</p>",
  "apple_music_embed": "https://embed.music.apple.com/jp/album/hang-on-in-there/1516960329?i=1516960333",
  "amazon_url": "https://amzn.to/4qOOTtO",
  "season": [
    "fall",
    "winter"
  ],
  "weather": [
    "cloudy",
    "rainy"
  ],
  "mood": [
    "mid"
  ],
  "country": [
    "USA"
  ],
  "city": [
    "Detroit"
  ]
}
