{
  "date": "2026-01-07",
  "title": "Right Down Here – Asha Puthli",
  "comment": "<p>ゆったりと渦を巻く鍵盤やギターと高音・低音を見事に使い分けるヴォーカル。<br>ソウル〜ジャズのムードとバレアリックな浮遊感が溶け合うトリップ感のある一曲。</p><p>Swirling, laid-back keys and guitar, paired with vocals that glide effortlessly between highs and lows.<br>A trippy track where soul-jazz moods melt into a Balearic sense of float.</p>",
  "apple_music_embed": "https://embed.music.apple.com/jp/album/right-down-here/1525352938?i=1525352941",
  "amazon_url": "https://amzn.to/49w7lRL",
  "season": [
    "spring",
    "summer"
  ],
  "weather": [
    "sunny",
    "cloudy"
  ],
  "mood": [
    "low",
    "mid"
  ],
  "country": [
    "India"
  ],
  "city": [
    "Mumbai"
  ]
}
