{
  "date": "2026-04-28",
  "title": "The End of a Love Affair – Julie London",
  "comment": "<p>静かに沈むようなアンサンブルの上で哀愁漂うヴォーカルが淡く揺れる。<br>夜更けのムードと失恋の余韻がにじむ、スモーキーな一曲。</p><p>Over a quiet ensemble, a wistful vocal sways softly.<br>A smoky track tinged with late-night mood and the aftertaste of heartbreak.</p>",
  "apple_music_embed": "https://embed.music.apple.com/jp/album/the-end-of-a-love-affair/724453421?i=724454649",
  "amazon_url": "https://amzn.to/4cjQ0Mb",
  "season": [
    "fall",
    "winter"
  ],
  "weather": [
    "cloudy",
    "rainy"
  ],
  "mood": [
    "low",
    "mid"
  ],
  "country": [
    "USA"
  ],
  "city": [
    "Los Angeles"
  ]
}
